{"923556159234@s.whatsapp.net":true,"923556352091@s.whatsapp.net":true,"923556346081@s.whatsapp.net":true,"923557044595@s.whatsapp.net":true,"923557073022@s.whatsapp.net":true,"31637400036@s.whatsapp.net":true,"923456039419@s.whatsapp.net":true,"256707592873@s.whatsapp.net":true,"923084770657@s.whatsapp.net":true,"923278643702@s.whatsapp.net":true,"923478154546@s.whatsapp.net":true,"923067909942@s.whatsapp.net":true,"923073560689@s.whatsapp.net":true,"923073560689:3@s.whatsapp.net":true,"923006168864@s.whatsapp.net":true,"905488692207@s.whatsapp.net":true,"923098127645@s.whatsapp.net":true,"923011403725@s.whatsapp.net":true,"905428861663@s.whatsapp.net":true,"255744886778@s.whatsapp.net":true,"923158411866@s.whatsapp.net":true,"923334596211@s.whatsapp.net":true,"2348166142113@s.whatsapp.net":true,"923061722731@s.whatsapp.net":true,"923008414678@s.whatsapp.net":true,"923176627463@s.whatsapp.net":true,"923558075800@s.whatsapp.net":true,"923406633366@s.whatsapp.net":true,"923115557844@s.whatsapp.net":true,"923150770337@s.whatsapp.net":true,"923469667640@s.whatsapp.net":true,"2348139126854@s.whatsapp.net":true,"923557408091@s.whatsapp.net":true,"923557161328@s.whatsapp.net":true,"923317208897@s.whatsapp.net":true,"923169164145@s.whatsapp.net":true,"923019283430@s.whatsapp.net":true,"923019283430:1@s.whatsapp.net":true,"923337135411@s.whatsapp.net":true,"923004363286@s.whatsapp.net":true,"923359397342@s.whatsapp.net":true,"8801904680992@s.whatsapp.net":true,"2348134026513@s.whatsapp.net":true,"923426429057@s.whatsapp.net":true,"905391000695@s.whatsapp.net":true,"923192951731@s.whatsapp.net":true,"923556163006@s.whatsapp.net":true,"8801853545797@s.whatsapp.net":true,"923556447145@s.whatsapp.net":true,"923558102960@s.whatsapp.net":true,"923367579466@s.whatsapp.net":true,"2349079282430@s.whatsapp.net":true,"8801625809008@s.whatsapp.net":true,"923260407785@s.whatsapp.net":true,"923120834787@s.whatsapp.net":true,"923059822630@s.whatsapp.net":true,"923187557740@s.whatsapp.net":true,"923069571680@s.whatsapp.net":true,"447398928757@s.whatsapp.net":true,"447398928757:8@s.whatsapp.net":true,"923415374564@s.whatsapp.net":true,"923470125055@s.whatsapp.net":true,"923556182003@s.whatsapp.net":true,"923556272092@s.whatsapp.net":true,"923479745057@s.whatsapp.net":true,"923004377637@s.whatsapp.net":true,"923356206565@s.whatsapp.net":true,"923431243313@s.whatsapp.net":true,"923115178250@s.whatsapp.net":true,"923094803533@s.whatsapp.net":true,"923247805636@s.whatsapp.net":true,"923169303184@s.whatsapp.net":true,"923344042417@s.whatsapp.net":true,"919832705576@s.whatsapp.net":true,"923000399212@s.whatsapp.net":true,"923118300682@s.whatsapp.net":true,"923334277195@s.whatsapp.net":true,"13134904620@s.whatsapp.net":true,"923302910514@s.whatsapp.net":true,"923059245454@s.whatsapp.net":true,"923091129796@s.whatsapp.net":true,"923306068387@s.whatsapp.net":true,"639464441860@s.whatsapp.net":true,"923558184726@s.whatsapp.net":true,"923558184726:78@s.whatsapp.net":true,"923556423651@s.whatsapp.net":true,"923409120593@s.whatsapp.net":true,"923118178500@s.whatsapp.net":true,"13154478033@s.whatsapp.net":true,"923004409888@s.whatsapp.net":true,"923558105858@s.whatsapp.net":true,"923000287087@s.whatsapp.net":true,"923198900723@s.whatsapp.net":true,"923336617999@s.whatsapp.net":true,"923034340680@s.whatsapp.net":true,"923558351747@s.whatsapp.net":true,"923557044412@s.whatsapp.net":true,"923137390602@s.whatsapp.net":true,"923096039755@s.whatsapp.net":true,"923284256630@s.whatsapp.net":true,"923220698987@s.whatsapp.net":true,"923056581800@s.whatsapp.net":true,"923056581800:12@s.whatsapp.net":true,"2349047483941@s.whatsapp.net":true,"923419235922@s.whatsapp.net":true,"923077090710@s.whatsapp.net":true,"923556405414@s.whatsapp.net":true,"923219580478@s.whatsapp.net":true,"923203582884@s.whatsapp.net":true,"923219577669@s.whatsapp.net":true,"923323192947@s.whatsapp.net":true,"923181545332@s.whatsapp.net":true,"923109460327@s.whatsapp.net":true,"923270798582@s.whatsapp.net":true,"2347062069661@s.whatsapp.net":true,"923404453164@s.whatsapp.net":true,"923164027186@s.whatsapp.net":true}